{
  "name": "Ethereum Sepolia",
  "chainId": 11155111,
  "rpc": "https://ethereum-sepolia-rpc.publicnode.com",
  "explorer": "https://sepolia.etherscan.io",
  "deployments": {
    "vault": {
      "address": "0x67709C7Ee06912611976Ab527c9041BCee7aB0F7",
      "pauseWindowDuration": 7776000,
      "bufferPeriodDuration": 2592000
    },
    "protocolFeeController": {
      "maxYieldValue": "50000000000000000",
      "maxAumValue": "50000000000000000"
    },
    "pools": {
      "weightedPoolFactory": {
        "pauseWindowDuration": 7776000
      },
      "stablePoolFactory": {
        "pauseWindowDuration": 7776000
      }
    }
  },
  "tokens": {
    "WETH": "0xfFf9976782d46CC05630D1f6eBAb18b2324d6B14",
    "DAI": "0xFF34B3d4Aee8ddCd6F9AFFFB6Fe49bD371b8a357",
    "USDC": "0x94a9D9AC8a22534E3FaCa9F4e7F2E2cf85d5E4C8"
  },
  "routerVersion": "1.0.0"
}
